setup.py
Sqlchemyforms.egg-info/PKG-INFO
Sqlchemyforms.egg-info/SOURCES.txt
Sqlchemyforms.egg-info/dependency_links.txt
Sqlchemyforms.egg-info/requires.txt
Sqlchemyforms.egg-info/top_level.txt
sqlchemyforms/__init__.py
sqlchemyforms/crud_base.py
sqlchemyforms/database.py
sqlchemyforms/exceptions.py
sqlchemyforms/field.py
sqlchemyforms/form.py
sqlchemyforms/tools.py
sqlchemyforms/widget.py
sqlchemyforms/widget_factory.py
sqlchemyforms/table/__init__.py
sqlchemyforms/table/column.py
sqlchemyforms/table/data_table.py
sqlchemyforms/validators/__init__.py
sqlchemyforms/validators/is_in_db.py
sqlchemyforms/validators/is_in_set.py
sqlchemyforms/validators/simple.py