Metadata-Version: 1.0
Name: Sqlchemyforms
Version: 1.0
Summary: Generate form objects for create HTML forms based on SQLAlchhemy models
Home-page: https://github.com/voidpp/sqlchemyforms
Author: Lajos Santa
Author-email: santa.lajos@coldline.hu
License: MIT
Platform: UNKNOWN
